MANIFEST.in
README.rst
setup.py
aesmix/__init__.py
aesmix/keyreg.py
aesmix/manager.py
aesmix/padder.py
aesmix/wrapper.py
aesmix.egg-info/PKG-INFO
aesmix.egg-info/SOURCES.txt
aesmix.egg-info/dependency_links.txt
aesmix.egg-info/not-zip-safe
aesmix.egg-info/requires.txt
aesmix.egg-info/top_level.txt
lib/build_aesmix.py
lib/includes/aes_mix.h
lib/includes/aes_mix_multi.h
lib/includes/aes_mix_multi_oaep.h
lib/includes/aes_mix_oaep.h
lib/includes/aes_mixslice.h
lib/includes/debug.h
lib/src/aes_mix.c
lib/src/aes_mix_multi.c
lib/src/aes_mix_multi_oaep.c
lib/src/aes_mix_oaep.c
lib/src/aes_mixslice.c
lib/src/debug.c
scripts/mixslice