Metadata-Version: 1.0
Name: aesmix
Version: 1.6
Summary: Mix&Slice
Home-page: http://github.com/unibg-seclab/aesmix
Author: Unibg Seclab
Author-email: seclab@unibg.it
License: MIT
Platform: UNKNOWN
